<?xml version="1.0"?>
<PlannerResult>
	<PlannerName>rev45 [MC-UCT -i [IDS]]</PlannerName>
	<BenchmarkSet>IPPC2011</BenchmarkSet>
	<NumberOfRuns>100</NumberOfRuns>
	<Time>278024.18</Time>

	<Domain>
		<DomainName>elevators</DomainName>
		<Time>47329.83</Time>

		<Problem>
			<ProblemName>10</ProblemName>
			<AvgReward>-72.64</AvgReward>
			<Confidence95>6.16</Confidence95>
			<Time>4994.4</Time>
		</Problem>

		<Problem>
			<ProblemName>1</ProblemName>
			<AvgReward>-44.79</AvgReward>
			<Confidence95>2.33</Confidence95>
			<Time>4722.61</Time>
		</Problem>

		<Problem>
			<ProblemName>3</ProblemName>
			<AvgReward>-57.03</AvgReward>
			<Confidence95>1.74</Confidence95>
			<Time>4594.14</Time>
		</Problem>

		<Problem>
			<ProblemName>2</ProblemName>
			<AvgReward>-16.78</AvgReward>
			<Confidence95>1.64</Confidence95>
			<Time>4639.72</Time>
		</Problem>

		<Problem>
			<ProblemName>5</ProblemName>
			<AvgReward>-55.28</AvgReward>
			<Confidence95>3.32</Confidence95>
			<Time>4642.41</Time>
		</Problem>

		<Problem>
			<ProblemName>4</ProblemName>
			<AvgReward>-52.44</AvgReward>
			<Confidence95>3.43</Confidence95>
			<Time>4920.7</Time>
		</Problem>

		<Problem>
			<ProblemName>7</ProblemName>
			<AvgReward>-85.33</AvgReward>
			<Confidence95>5.25</Confidence95>
			<Time>4913.06</Time>
		</Problem>

		<Problem>
			<ProblemName>6</ProblemName>
			<AvgReward>-72.26</AvgReward>
			<Confidence95>3.32</Confidence95>
			<Time>4613.7</Time>
		</Problem>

		<Problem>
			<ProblemName>9</ProblemName>
			<AvgReward>-97.3</AvgReward>
			<Confidence95>4.49</Confidence95>
			<Time>4664.37</Time>
		</Problem>

		<Problem>
			<ProblemName>8</ProblemName>
			<AvgReward>-77.84</AvgReward>
			<Confidence95>4.29</Confidence95>
			<Time>4624.72</Time>
		</Problem>

	</Domain>

	<Domain>
		<DomainName>sysadmin</DomainName>
		<Time>44760.52</Time>

		<Problem>
			<ProblemName>10</ProblemName>
			<AvgReward>513.78</AvgReward>
			<Confidence95>11.28</Confidence95>
			<Time>4200.92</Time>
		</Problem>

		<Problem>
			<ProblemName>1</ProblemName>
			<AvgReward>335.19</AvgReward>
			<Confidence95>4.16</Confidence95>
			<Time>5654.11</Time>
		</Problem>

		<Problem>
			<ProblemName>3</ProblemName>
			<AvgReward>513.43</AvgReward>
			<Confidence95>13.4</Confidence95>
			<Time>5018.72</Time>
		</Problem>

		<Problem>
			<ProblemName>2</ProblemName>
			<AvgReward>310.75</AvgReward>
			<Confidence95>7.9</Confidence95>
			<Time>3681.4</Time>
		</Problem>

		<Problem>
			<ProblemName>5</ProblemName>
			<AvgReward>527.97</AvgReward>
			<Confidence95>11.64</Confidence95>
			<Time>4166.36</Time>
		</Problem>

		<Problem>
			<ProblemName>4</ProblemName>
			<AvgReward>449.61</AvgReward>
			<Confidence95>13.56</Confidence95>
			<Time>5044.04</Time>
		</Problem>

		<Problem>
			<ProblemName>7</ProblemName>
			<AvgReward>559.66</AvgReward>
			<Confidence95>11.51</Confidence95>
			<Time>4289.02</Time>
		</Problem>

		<Problem>
			<ProblemName>6</ProblemName>
			<AvgReward>457.64</AvgReward>
			<Confidence95>11.12</Confidence95>
			<Time>4344.2</Time>
		</Problem>

		<Problem>
			<ProblemName>9</ProblemName>
			<AvgReward>680.88</AvgReward>
			<Confidence95>12.19</Confidence95>
			<Time>4149.59</Time>
		</Problem>

		<Problem>
			<ProblemName>8</ProblemName>
			<AvgReward>450.19</AvgReward>
			<Confidence95>10.04</Confidence95>
			<Time>4212.16</Time>
		</Problem>

	</Domain>

	<Domain>
		<DomainName>recon</DomainName>
		<Time>45695.38</Time>

		<Problem>
			<ProblemName>10</ProblemName>
			<AvgReward>5.88</AvgReward>
			<Confidence95>0.09</Confidence95>
			<Time>4736.48</Time>
		</Problem>

		<Problem>
			<ProblemName>1</ProblemName>
			<AvgReward>3.86</AvgReward>
			<Confidence95>0.27</Confidence95>
			<Time>4612.5</Time>
		</Problem>

		<Problem>
			<ProblemName>3</ProblemName>
			<AvgReward>14.06</AvgReward>
			<Confidence95>0.11</Confidence95>
			<Time>4304.65</Time>
		</Problem>

		<Problem>
			<ProblemName>2</ProblemName>
			<AvgReward>3.16</AvgReward>
			<Confidence95>0.2</Confidence95>
			<Time>4824.92</Time>
		</Problem>

		<Problem>
			<ProblemName>5</ProblemName>
			<AvgReward>14.61</AvgReward>
			<Confidence95>0.18</Confidence95>
			<Time>4684.16</Time>
		</Problem>

		<Problem>
			<ProblemName>4</ProblemName>
			<AvgReward>2.63</AvgReward>
			<Confidence95>0.13</Confidence95>
			<Time>4562.37</Time>
		</Problem>

		<Problem>
			<ProblemName>7</ProblemName>
			<AvgReward>5.22</AvgReward>
			<Confidence95>0.07</Confidence95>
			<Time>4784.34</Time>
		</Problem>

		<Problem>
			<ProblemName>6</ProblemName>
			<AvgReward>10.63</AvgReward>
			<Confidence95>0.09</Confidence95>
			<Time>4310.38</Time>
		</Problem>

		<Problem>
			<ProblemName>9</ProblemName>
			<AvgReward>9.75</AvgReward>
			<Confidence95>0.2</Confidence95>
			<Time>4633.09</Time>
		</Problem>

		<Problem>
			<ProblemName>8</ProblemName>
			<AvgReward>10.35</AvgReward>
			<Confidence95>0.07</Confidence95>
			<Time>4242.49</Time>
		</Problem>

	</Domain>

	<Domain>
		<DomainName>game</DomainName>
		<Time>47047.85</Time>

		<Problem>
			<ProblemName>10</ProblemName>
			<AvgReward>560.34</AvgReward>
			<Confidence95>6.97</Confidence95>
			<Time>4094.85</Time>
		</Problem>

		<Problem>
			<ProblemName>1</ProblemName>
			<AvgReward>206.84</AvgReward>
			<Confidence95>3.0</Confidence95>
			<Time>5369.89</Time>
		</Problem>

		<Problem>
			<ProblemName>3</ProblemName>
			<AvgReward>147.14</AvgReward>
			<Confidence95>5.26</Confidence95>
			<Time>5405.36</Time>
		</Problem>

		<Problem>
			<ProblemName>2</ProblemName>
			<AvgReward>131.66</AvgReward>
			<Confidence95>8.52</Confidence95>
			<Time>5416.35</Time>
		</Problem>

		<Problem>
			<ProblemName>5</ProblemName>
			<AvgReward>297.64</AvgReward>
			<Confidence95>7.17</Confidence95>
			<Time>4817.75</Time>
		</Problem>

		<Problem>
			<ProblemName>4</ProblemName>
			<AvgReward>345.84</AvgReward>
			<Confidence95>3.86</Confidence95>
			<Time>4903.6</Time>
		</Problem>

		<Problem>
			<ProblemName>7</ProblemName>
			<AvgReward>468.23</AvgReward>
			<Confidence95>6.74</Confidence95>
			<Time>4060.02</Time>
		</Problem>

		<Problem>
			<ProblemName>6</ProblemName>
			<AvgReward>272.02</AvgReward>
			<Confidence95>4.94</Confidence95>
			<Time>4816.3</Time>
		</Problem>

		<Problem>
			<ProblemName>9</ProblemName>
			<AvgReward>407.65</AvgReward>
			<Confidence95>7.58</Confidence95>
			<Time>4081.72</Time>
		</Problem>

		<Problem>
			<ProblemName>8</ProblemName>
			<AvgReward>434.4</AvgReward>
			<Confidence95>8.38</Confidence95>
			<Time>4082.01</Time>
		</Problem>

	</Domain>

	<Domain>
		<DomainName>traffic</DomainName>
		<Time>40120.43</Time>

		<Problem>
			<ProblemName>10</ProblemName>
			<AvgReward>-127.32</AvgReward>
			<Confidence95>5.76</Confidence95>
			<Time>4193.7</Time>
		</Problem>

		<Problem>
			<ProblemName>1</ProblemName>
			<AvgReward>-8.32</AvgReward>
			<Confidence95>0.94</Confidence95>
			<Time>3833.05</Time>
		</Problem>

		<Problem>
			<ProblemName>3</ProblemName>
			<AvgReward>-29.49</AvgReward>
			<Confidence95>2.66</Confidence95>
			<Time>3933.77</Time>
		</Problem>

		<Problem>
			<ProblemName>2</ProblemName>
			<AvgReward>-19.0</AvgReward>
			<Confidence95>1.14</Confidence95>
			<Time>3800.87</Time>
		</Problem>

		<Problem>
			<ProblemName>5</ProblemName>
			<AvgReward>-52.72</AvgReward>
			<Confidence95>3.71</Confidence95>
			<Time>3951.1</Time>
		</Problem>

		<Problem>
			<ProblemName>4</ProblemName>
			<AvgReward>-72.29</AvgReward>
			<Confidence95>3.21</Confidence95>
			<Time>3940.06</Time>
		</Problem>

		<Problem>
			<ProblemName>7</ProblemName>
			<AvgReward>-52.25</AvgReward>
			<Confidence95>2.91</Confidence95>
			<Time>4169.31</Time>
		</Problem>

		<Problem>
			<ProblemName>6</ProblemName>
			<AvgReward>-83.25</AvgReward>
			<Confidence95>5.11</Confidence95>
			<Time>3979.75</Time>
		</Problem>

		<Problem>
			<ProblemName>9</ProblemName>
			<AvgReward>-23.32</AvgReward>
			<Confidence95>2.8</Confidence95>
			<Time>4201.15</Time>
		</Problem>

		<Problem>
			<ProblemName>8</ProblemName>
			<AvgReward>-74.11</AvgReward>
			<Confidence95>5.96</Confidence95>
			<Time>4117.67</Time>
		</Problem>

	</Domain>

	<Domain>
		<DomainName>crossing</DomainName>
		<Time>8701.52</Time>

		<Problem>
			<ProblemName>10</ProblemName>
			<AvgReward>-32.2</AvgReward>
			<Confidence95>2.51</Confidence95>
			<Time>890.09</Time>
		</Problem>

		<Problem>
			<ProblemName>1</ProblemName>
			<AvgReward>-4.63</AvgReward>
			<Confidence95>0.21</Confidence95>
			<Time>491.01</Time>
		</Problem>

		<Problem>
			<ProblemName>3</ProblemName>
			<AvgReward>-6.68</AvgReward>
			<Confidence95>0.41</Confidence95>
			<Time>708.88</Time>
		</Problem>

		<Problem>
			<ProblemName>2</ProblemName>
			<AvgReward>-5.44</AvgReward>
			<Confidence95>0.34</Confidence95>
			<Time>575.41</Time>
		</Problem>

		<Problem>
			<ProblemName>5</ProblemName>
			<AvgReward>-8.08</AvgReward>
			<Confidence95>0.44</Confidence95>
			<Time>853.56</Time>
		</Problem>

		<Problem>
			<ProblemName>4</ProblemName>
			<AvgReward>-12.01</AvgReward>
			<Confidence95>1.06</Confidence95>
			<Time>1246.7</Time>
		</Problem>

		<Problem>
			<ProblemName>7</ProblemName>
			<AvgReward>-17.32</AvgReward>
			<Confidence95>2.68</Confidence95>
			<Time>942.48</Time>
		</Problem>

		<Problem>
			<ProblemName>6</ProblemName>
			<AvgReward>-11.14</AvgReward>
			<Confidence95>0.78</Confidence95>
			<Time>1166.65</Time>
		</Problem>

		<Problem>
			<ProblemName>9</ProblemName>
			<AvgReward>-16.12</AvgReward>
			<Confidence95>2.87</Confidence95>
			<Time>820.26</Time>
		</Problem>

		<Problem>
			<ProblemName>8</ProblemName>
			<AvgReward>-27.03</AvgReward>
			<Confidence95>2.73</Confidence95>
			<Time>1006.48</Time>
		</Problem>

	</Domain>

	<Domain>
		<DomainName>skill</DomainName>
		<Time>28438.61</Time>

		<Problem>
			<ProblemName>10</ProblemName>
			<AvgReward>-191.74</AvgReward>
			<Confidence95>37.44</Confidence95>
			<Time>2771.57</Time>
		</Problem>

		<Problem>
			<ProblemName>1</ProblemName>
			<AvgReward>65.4</AvgReward>
			<Confidence95>1.84</Confidence95>
			<Time>2885.33</Time>
		</Problem>

		<Problem>
			<ProblemName>3</ProblemName>
			<AvgReward>83.91</AvgReward>
			<Confidence95>14.26</Confidence95>
			<Time>3049.14</Time>
		</Problem>

		<Problem>
			<ProblemName>2</ProblemName>
			<AvgReward>76.45</AvgReward>
			<Confidence95>2.42</Confidence95>
			<Time>3144.86</Time>
		</Problem>

		<Problem>
			<ProblemName>5</ProblemName>
			<AvgReward>-15.86</AvgReward>
			<Confidence95>24.6</Confidence95>
			<Time>2708.37</Time>
		</Problem>

		<Problem>
			<ProblemName>4</ProblemName>
			<AvgReward>94.87</AvgReward>
			<Confidence95>15.11</Confidence95>
			<Time>2978.34</Time>
		</Problem>

		<Problem>
			<ProblemName>7</ProblemName>
			<AvgReward>-87.58</AvgReward>
			<Confidence95>28.07</Confidence95>
			<Time>2583.43</Time>
		</Problem>

		<Problem>
			<ProblemName>6</ProblemName>
			<AvgReward>29.28</AvgReward>
			<Confidence95>25.77</Confidence95>
			<Time>2937.56</Time>
		</Problem>

		<Problem>
			<ProblemName>9</ProblemName>
			<AvgReward>-179.57</AvgReward>
			<Confidence95>35.75</Confidence95>
			<Time>2805.31</Time>
		</Problem>

		<Problem>
			<ProblemName>8</ProblemName>
			<AvgReward>-174.74</AvgReward>
			<Confidence95>42.33</Confidence95>
			<Time>2574.7</Time>
		</Problem>

	</Domain>

	<Domain>
		<DomainName>navigation</DomainName>
		<Time>15930.04</Time>

		<Problem>
			<ProblemName>10</ProblemName>
			<AvgReward>-38.83</AvgReward>
			<Confidence95>0.56</Confidence95>
			<Time>2279.1</Time>
		</Problem>

		<Problem>
			<ProblemName>1</ProblemName>
			<AvgReward>-11.3</AvgReward>
			<Confidence95>1.68</Confidence95>
			<Time>874.96</Time>
		</Problem>

		<Problem>
			<ProblemName>3</ProblemName>
			<AvgReward>-14.77</AvgReward>
			<Confidence95>1.67</Confidence95>
			<Time>1171.42</Time>
		</Problem>

		<Problem>
			<ProblemName>2</ProblemName>
			<AvgReward>-11.84</AvgReward>
			<Confidence95>1.15</Confidence95>
			<Time>1075.56</Time>
		</Problem>

		<Problem>
			<ProblemName>5</ProblemName>
			<AvgReward>-20.95</AvgReward>
			<Confidence95>1.37</Confidence95>
			<Time>1794.37</Time>
		</Problem>

		<Problem>
			<ProblemName>4</ProblemName>
			<AvgReward>-18.36</AvgReward>
			<Confidence95>1.94</Confidence95>
			<Time>1349.62</Time>
		</Problem>

		<Problem>
			<ProblemName>7</ProblemName>
			<AvgReward>-24.49</AvgReward>
			<Confidence95>0.75</Confidence95>
			<Time>2388.94</Time>
		</Problem>

		<Problem>
			<ProblemName>6</ProblemName>
			<AvgReward>-23.15</AvgReward>
			<Confidence95>0.99</Confidence95>
			<Time>2150.36</Time>
		</Problem>

		<Problem>
			<ProblemName>9</ProblemName>
			<AvgReward>-38.25</AvgReward>
			<Confidence95>1.01</Confidence95>
			<Time>1749.97</Time>
		</Problem>

		<Problem>
			<ProblemName>8</ProblemName>
			<AvgReward>-31.65</AvgReward>
			<Confidence95>2.37</Confidence95>
			<Time>1095.74</Time>
		</Problem>

	</Domain>

</PlannerResult>
